CHANGES.rst
CONTRIBUTORS.rst
MANIFEST.in
README.rst
setup.cfg
setup.py
docs/LICENSE.GPL
docs/LICENSE.txt
docs/localrole.png
src/sc/__init__.py
src/sc.contentrules.localrole.egg-info/PKG-INFO
src/sc.contentrules.localrole.egg-info/SOURCES.txt
src/sc.contentrules.localrole.egg-info/dependency_links.txt
src/sc.contentrules.localrole.egg-info/entry_points.txt
src/sc.contentrules.localrole.egg-info/namespace_packages.txt
src/sc.contentrules.localrole.egg-info/not-zip-safe
src/sc.contentrules.localrole.egg-info/requires.txt
src/sc.contentrules.localrole.egg-info/top_level.txt
src/sc/contentrules/__init__.py
src/sc/contentrules/localrole/__init__.py
src/sc/contentrules/localrole/action.py
src/sc/contentrules/localrole/configure.zcml
src/sc/contentrules/localrole/interfaces.py
src/sc/contentrules/localrole/testing.py
src/sc/contentrules/localrole/vocabulary.py
src/sc/contentrules/localrole/locales/manual.pot
src/sc/contentrules/localrole/locales/plone.pot
src/sc/contentrules/localrole/locales/sc.contentrules.localrole.pot
src/sc/contentrules/localrole/locales/en/LC_MESSAGES/sc.contentrules.localrole.po
src/sc/contentrules/localrole/locales/es/LC_MESSAGES/plone.po
src/sc/contentrules/localrole/locales/es/LC_MESSAGES/sc.contentrules.localrole.po
src/sc/contentrules/localrole/locales/pt_BR/LC_MESSAGES/plone.po
src/sc/contentrules/localrole/locales/pt_BR/LC_MESSAGES/sc.contentrules.localrole.po
src/sc/contentrules/localrole/tests/__init__.py
src/sc/contentrules/localrole/tests/test_localroles.py
src/sc/contentrules/localrole/tests/test_vocabularies.py